DESCRIPTION.rst
MANIFEST.in
README.md
RELEASE-VERSION
setup.cfg
setup.py
version.py
mightex_device/__init__.py
mightex_device/mightex_device.py
mightex_device.egg-info/PKG-INFO
mightex_device.egg-info/SOURCES.txt
mightex_device.egg-info/dependency_links.txt
mightex_device.egg-info/requires.txt
mightex_device.egg-info/top_level.txt