Metadata-Version: 1.1
Name: mightex_device
Version: 1.2
Summary: Interface to Mightex LED controllers.
Home-page: https://github.com/janelia-pypi/mightex_device_python
Author: Peter Polidoro
Author-email: polidorop@janelia.hhmi.org
License: BSD
Keywords: mightex led serial device
Platform: UNKNOWN
Classifier: Development Status :: 4 - Beta
Classifier: Intended Audience :: Developers
Classifier: Topic :: Software Development :: Build Tools
Classifier: License :: OSI Approved :: BSD License
Classifier: Programming Language :: Python :: 2.7
